tourbillon_redis-0.4.2-py3.4-nspkg.pth
tourbillon/redis/__init__.py
tourbillon/redis/redis2.py
tourbillon_redis-0.4.2.dist-info/DESCRIPTION.rst
tourbillon_redis-0.4.2.dist-info/METADATA
tourbillon_redis-0.4.2.dist-info/RECORD
tourbillon_redis-0.4.2.dist-info/WHEEL
tourbillon_redis-0.4.2.dist-info/metadata.json
tourbillon_redis-0.4.2.dist-info/namespace_packages.txt
tourbillon_redis-0.4.2.dist-info/top_level.txt
